.gitignore
LICENSE
README.md
pyproject.toml
setup.py
.github/workflows/deploy.yml
.github/workflows/test.yml
src/pyspral/.gitignore
src/pyspral/__init__.py
src/pyspral/csc.c
src/pyspral/csc.pxd
src/pyspral/csc.pyx
src/pyspral/lsmr.c
src/pyspral/lsmr.pyx
src/pyspral/random_matrix.c
src/pyspral/random_matrix.pyx
src/pyspral/rb.c
src/pyspral/rb.pyx
src/pyspral/scaling.c
src/pyspral/scaling.pyx
src/pyspral/ssids.c
src/pyspral/ssids.pyx
src/pyspral/ssmfe.c
src/pyspral/ssmfe.pyx
src/pyspral/types.c
src/pyspral/types.pxd
src/pyspral/types.pyx
src/pyspral.egg-info/PKG-INFO
src/pyspral.egg-info/SOURCES.txt
src/pyspral.egg-info/dependency_links.txt
src/pyspral.egg-info/requires.txt
src/pyspral.egg-info/top_level.txt
tests/__init__.py
tests/test_lsmr.py
tests/test_random_matrix.py
tests/test_rb.py
tests/test_scaling.py
tests/test_ssids.py
tests/test_ssmfe.py
tests/resources/__init__.py
tests/resources/matrix.rb