Metadata-Version: 2.1
Name: pyspral
Version: 0.1.6
Summary: Python bindings to the Sparse Parallel Robust Algorithms Library
Author-email: Christoph Hansknecht <christoph.hansknecht@tu-clausthal.de>
License:                     GNU GENERAL PUBLIC LICENSE
Project-URL: Repository, https://github.com/chrhansk/pyspral
Classifier: Development Status :: 4 - Beta
Classifier: Intended Audience :: Science/Research
License-File: LICENSE
Requires-Dist: scipy
Requires-Dist: numpy
